apce/__init__.py
apce/core.py
apce/compliance/__init__.py
apce/compliance/watermark.py
apce/utils/__init__.py
apce/utils/hash.py
apce/wrappers/__init__.py
apce/wrappers/anthropic.py
apce/wrappers/base.py
apce/wrappers/llama.py
apce/wrappers/openai.py
apce_safety-0.2.2.dist-info/LICENSE
apce_safety-0.2.2.dist-info/METADATA
apce_safety-0.2.2.dist-info/WHEEL
apce_safety-0.2.2.dist-info/entry_points.txt
apce_safety-0.2.2.dist-info/top_level.txt
apce_safety-0.2.2.dist-info/RECORD
