Metadata-Version: 2.1
Name: apce-safety
Version: 0.2.2
Summary: AI Governance with Conservation Laws - Runtime Verification for Transformers
Home-page: https://github.com/atomic-trust/apce-safety
Author: Rafael Velado
Author-email: raf@atomic-trust.com
Project-URL: Documentation, https://atomic-trust.com/docs
Project-URL: Source, https://github.com/atomic-trust/apce-safety
Project-URL: Bug Tracker, https://github.com/atomic-trust/apce-safety/issues
Keywords: ai-safety,llm,transformer,verification,governance,compliance,eu-ai-act,nist,adversarial,provenance,audit,cryptography
Classifier: Development Status :: 4 - Beta
Classifier: Intended Audience :: Developers
Classifier: Intended Audience :: Science/Research
Classifier: License :: OSI Approved :: Apache Software License
Classifier: Operating System :: OS Independent
Classifier: Programming Language :: Python :: 3
Classifier: Programming Language :: Python :: 3.9
Classifier: Programming Language :: Python :: 3.10
Classifier: Programming Language :: Python :: 3.11
Classifier: Programming Language :: Python :: 3.12
Classifier: Topic :: Scientific/Engineering :: Artificial Intelligence
Classifier: Topic :: Security :: Cryptography
Classifier: Topic :: Software Development :: Libraries :: Python Modules
Requires-Python: >=3.9
License-File: LICENSE
Requires-Dist: numpy >=1.21.0
Requires-Dist: blake3 >=0.3.0
Requires-Dist: pydantic >=2.0.0
Provides-Extra: anthropic
Requires-Dist: anthropic >=0.18.0 ; extra == 'anthropic'
Provides-Extra: dev
Requires-Dist: pytest >=7.0.0 ; extra == 'dev'
Requires-Dist: pytest-cov >=4.0.0 ; extra == 'dev'
Requires-Dist: black >=23.0.0 ; extra == 'dev'
Requires-Dist: mypy >=1.0.0 ; extra == 'dev'
Requires-Dist: ruff >=0.1.0 ; extra == 'dev'
Provides-Extra: full
Requires-Dist: anthropic >=0.18.0 ; extra == 'full'
Requires-Dist: openai >=1.0.0 ; extra == 'full'
Requires-Dist: transformers >=4.35.0 ; extra == 'full'
Requires-Dist: torch >=2.0.0 ; extra == 'full'
Provides-Extra: llama
Requires-Dist: transformers >=4.35.0 ; extra == 'llama'
Requires-Dist: torch >=2.0.0 ; extra == 'llama'
Provides-Extra: openai
Requires-Dist: openai >=1.0.0 ; extra == 'openai'
